<?xml version="1.0" encoding="UTF-8"?>
<AuditTrail>
<Entry type="ExecutionReport" msgId="211324649">
	<field tag="35" val="8"/>
	<field tag="34" val="000016"/>
	<field tag="43" val="N"/>
	<field tag="52" val="20110223-02:45:08"/>
	<field tag="6556" val="today12"/>
	<field tag="17" val="68113.1298429108.0"/>
	<field tag="32" val="*"/>
</Entry>
<Entry type="Acknowledged" msgId="3550857113">
	<field tag="35" val="8"/>
	<field tag="34" val="000021"/>
	<field tag="43" val="N"/>
	<field tag="52" val="20110223-02:45:14"/>
	<field tag="11" val="*"/>
	<field tag="17" val="68113.1298429114.0"/>
	<field tag="150" val="0"/>
	<field tag="20" val="3"/>
	<field tag="39" val="0"/>
	<field tag="55" val="*"/>
	<field tag="38" val="0"/>
	<field tag="44" val="nan"/>
	<field tag="32" val="0"/>
	<field tag="31" val="0.00"/>
	<field tag="14" val="0"/>
	<field tag="151" val="0"/>
	<field tag="6" val="0"/>
	<field tag="54" val="1"/>
	<field tag="37" val="*"/>
	<field tag="60" val="20110223-02:45:14"/>
	<field tag="40" val="2"/>
	<field tag="59" val="0"/>
</Entry>
<Entry type="ExecutionReport" msgId="1603934634">
	<field tag="35" val="8"/>
	<field tag="34" val="000004"/>
	<field tag="43" val="N"/>
	<field tag="52" val="20110223-05:23:42"/>
	<field tag="6556" val="today585"/>
	<field tag="17" val="68113.1298438622.0"/>
	<field tag="32" val="*"/>
</Entry>
<Entry type="Acknowledged" msgId="2993940295">
	<field tag="35" val="8"/>
	<field tag="34" val="000008"/>
	<field tag="43" val="N"/>
	<field tag="52" val="20110223-05:23:43"/>
	<field tag="11" val="*"/>
	<field tag="17" val="68113.1298438623.0"/>
	<field tag="150" val="0"/>
	<field tag="20" val="3"/>
	<field tag="39" val="0"/>
	<field tag="55" val="*"/>
	<field tag="38" val="0"/>
	<field tag="44" val="nan"/>
	<field tag="32" val="0"/>
	<field tag="31" val="0.00"/>
	<field tag="14" val="0"/>
	<field tag="151" val="0"/>
	<field tag="6" val="0"/>
	<field tag="54" val="1"/>
	<field tag="37" val="*"/>
	<field tag="60" val="20110223-05:23:43"/>
	<field tag="40" val="2"/>
	<field tag="59" val="0"/>
</Entry>
<Entry type="ExecutionReport" msgId="3708072240">
	<field tag="35" val="8"/>
	<field tag="34" val="000002"/>
	<field tag="43" val="N"/>
	<field tag="52" val="20110223-08:16:50"/>
	<field tag="6556" val="today1200"/>
	<field tag="17" val="68113.1298449010.0"/>
	<field tag="32" val="*"/>
</Entry>
<Entry type="Acknowledged" msgId="1858285978">
	<field tag="35" val="8"/>
	<field tag="34" val="000004"/>
	<field tag="43" val="N"/>
	<field tag="52" val="20110223-08:16:50"/>
	<field tag="11" val="*"/>
	<field tag="17" val="68113.1298449010.1"/>
	<field tag="150" val="0"/>
	<field tag="20" val="3"/>
	<field tag="39" val="0"/>
	<field tag="55" val="*"/>
	<field tag="38" val="0"/>
	<field tag="44" val="nan"/>
	<field tag="32" val="0"/>
	<field tag="31" val="0.00"/>
	<field tag="14" val="0"/>
	<field tag="151" val="0"/>
	<field tag="6" val="0"/>
	<field tag="54" val="1"/>
	<field tag="37" val="*"/>
	<field tag="60" val="20110223-08:16:50"/>
	<field tag="40" val="2"/>
	<field tag="59" val="0"/>
</Entry>
<Entry type="ExecutionReport" msgId="1372984852">
	<field tag="35" val="8"/>
	<field tag="34" val="000016"/>
	<field tag="43" val="N"/>
	<field tag="52" val="20110223-08:19:54"/>
	<field tag="6556" val="today12"/>
	<field tag="17" val="68113.1298449194.0"/>
	<field tag="32" val="*"/>
</Entry>
<Entry type="Acknowledged" msgId="2684792959">
	<field tag="35" val="8"/>
	<field tag="34" val="000021"/>
	<field tag="43" val="N"/>
	<field tag="52" val="20110223-08:19:59"/>
	<field tag="11" val="*"/>
	<field tag="17" val="68113.1298449199.0"/>
	<field tag="150" val="0"/>
	<field tag="20" val="3"/>
	<field tag="39" val="0"/>
	<field tag="55" val="*"/>
	<field tag="38" val="0"/>
	<field tag="44" val="nan"/>
	<field tag="32" val="0"/>
	<field tag="31" val="0.00"/>
	<field tag="14" val="0"/>
	<field tag="151" val="0"/>
	<field tag="6" val="0"/>
	<field tag="54" val="1"/>
	<field tag="37" val="*"/>
	<field tag="60" val="20110223-08:19:59"/>
	<field tag="40" val="2"/>
	<field tag="59" val="0"/>
</Entry>
<Entry type="ExecutionReport" msgId="3033737343">
	<field tag="35" val="8"/>
	<field tag="34" val="000005"/>
	<field tag="43" val="N"/>
	<field tag="52" val="20110223-22:15:30"/>
	<field tag="6556" val="today12"/>
	<field tag="17" val="68113.1298499330.0"/>
	<field tag="32" val="*"/>
</Entry>
<Entry type="Acknowledged" msgId="3412249749">
	<field tag="35" val="8"/>
	<field tag="34" val="000021"/>
	<field tag="43" val="N"/>
	<field tag="52" val="20110223-22:15:34"/>
	<field tag="11" val="*"/>
	<field tag="17" val="68113.1298499334.0"/>
	<field tag="150" val="0"/>
	<field tag="20" val="3"/>
	<field tag="39" val="0"/>
	<field tag="55" val="*"/>
	<field tag="38" val="0"/>
	<field tag="44" val="nan"/>
	<field tag="32" val="0"/>
	<field tag="31" val="0.00"/>
	<field tag="14" val="0"/>
	<field tag="151" val="0"/>
	<field tag="6" val="0"/>
	<field tag="54" val="1"/>
	<field tag="37" val="*"/>
	<field tag="60" val="20110223-22:15:34"/>
	<field tag="40" val="2"/>
	<field tag="59" val="0"/>
</Entry>
<Entry type="ExecutionReport" msgId="1448497696">
	<field tag="35" val="8"/>
	<field tag="34" val="000699"/>
	<field tag="43" val="N"/>
	<field tag="52" val="20110224-00:00:03"/>
	<field tag="6556" val="today287"/>
	<field tag="17" val="68113.1298505603.0"/>
	<field tag="32" val="*"/>
</Entry>
</AuditTrail>
